bspcq/__init__.py
bspcq/__main__.py
bspcq/bspcq.py
bspcq/tests.py
bspcq-0.1.58.dist-info/LICENSE
bspcq-0.1.58.dist-info/METADATA
bspcq-0.1.58.dist-info/WHEEL
bspcq-0.1.58.dist-info/entry_points.txt
bspcq-0.1.58.dist-info/top_level.txt
bspcq-0.1.58.dist-info/RECORD
